tri/__init__.py
tri/form/__init__.py
tri/form/views.py
tri/form/templates/tri_form/checkbox.html
tri/form/templates/tri_form/choice.html
tri/form/templates/tri_form/compact_form_row.html
tri/form/templates/tri_form/compact_form_row_checkbox.html
tri/form/templates/tri_form/create_or_edit_object_block.html
tri/form/templates/tri_form/errors.html
tri/form/templates/tri_form/heading.html
tri/form/templates/tri_form/input.html
tri/form/templates/tri_form/label.html
tri/form/templates/tri_form/non_editable.html
tri/form/templates/tri_form/radio.html
tri/form/templates/tri_form/table_form_row.html
tri/form/templates/tri_form/table_form_row_checkbox.html
tri/form/templates/tri_form/text.html
tri.form-1.6.1.dist-info/DESCRIPTION.rst
tri.form-1.6.1.dist-info/METADATA
tri.form-1.6.1.dist-info/RECORD
tri.form-1.6.1.dist-info/WHEEL
tri.form-1.6.1.dist-info/metadata.json
tri.form-1.6.1.dist-info/top_level.txt
