Metadata-Version: 2.0
Name: tri.form
Version: 1.6.1
Summary: tri.form is a form library
Home-page: UNKNOWN
Author: Anders Hovmöller
Author-email: anders.hovmoller@trioptima.com
License: BSD
Keywords: tri.form
Platform: UNKNOWN
Classifier: Development Status :: 2 - Pre-Alpha
Classifier: Intended Audience :: Developers
Classifier: License :: OSI Approved :: BSD License
Classifier: Natural Language :: English
Classifier: Programming Language :: Python :: 2
Classifier: Programming Language :: Python :: 2.6
Classifier: Programming Language :: Python :: 2.7
Classifier: Programming Language :: Python :: 3
Classifier: Programming Language :: Python :: 3.3
Requires-Dist: django (==1.7)
Requires-Dist: tri.declarative
Requires-Dist: tri.named-struct
Requires-Dist: tri.struct
